{
  "hash": "91b0c20f",
  "configHash": "bf6762f1",
  "lockfileHash": "b5d19612",
  "browserHash": "002d0466",
  "optimized": {
    "vue": {
      "src": "../../../node_modules/vue/dist/vue.runtime.esm-bundler.js",
      "file": "vue.js",
      "fileHash": "47562322",
      "needsInterop": false
    },
    "vitepress > @vue/devtools-api": {
      "src": "../../../node_modules/@vue/devtools-api/lib/esm/index.js",
      "file": "vitepress___@vue_devtools-api.js",
      "fileHash": "a2b7ba87",
      "needsInterop": false
    },
    "vitepress > @vueuse/core": {
      "src": "../../../node_modules/@vueuse/core/index.mjs",
      "file": "vitepress___@vueuse_core.js",
      "fileHash": "1ea9946c",
      "needsInterop": false
    },
    "@theme/index": {
      "src": "../../../node_modules/vitepress/dist/client/theme-default/index.js",
      "file": "@theme_index.js",
      "fileHash": "ca520f02",
      "needsInterop": false
    }
  },
  "chunks": {
    "chunk-IM4JLXM5": {
      "file": "chunk-IM4JLXM5.js"
    },
    "chunk-I27O6UFQ": {
      "file": "chunk-I27O6UFQ.js"
    }
  }
}